README.md
setup.py
Civilization.egg-info/PKG-INFO
Civilization.egg-info/SOURCES.txt
Civilization.egg-info/dependency_links.txt
Civilization.egg-info/not-zip-safe
Civilization.egg-info/top_level.txt
Factories/ArcherFactory.py
Factories/CavalryFactory.py
Factories/Factory.py
Factories/WarriorFactory.py
Factories/__init__.py
UnitStats/ArcherStats.py
UnitStats/CavalryStats.py
UnitStats/WarriorStats.py
UnitStats/__init__.py