Metadata-Version: 1.0
Name: Civilization
Version: 25347
Summary: Civ
Home-page: https://gitlab.com/pypri/pypri-gitlab-ci
Author: Dnet_n_Danya
Author-email: demisrus5554@gmail.com
License: None
Platform: UNKNOWN
